rcs_pydantic_automata/__init__.py
rcs_pydantic_automata/enums.py
rcs_pydantic_automata/errors.py
rcs_pydantic_automata/exceptions.py
rcs_pydantic_automata/main.py
rcs_pydantic_automata/scheme.py
rcs_pydantic_automata-1.0.1.dist-info/LICENSE
rcs_pydantic_automata-1.0.1.dist-info/METADATA
rcs_pydantic_automata-1.0.1.dist-info/WHEEL
rcs_pydantic_automata-1.0.1.dist-info/RECORD
