Metadata-Version: 2.3
Name: rcs-pydantic-automata
Version: 1.0.1
Summary: 
License: MIT
Keywords: pydantic,rcs,fastapi
Author: Danny Park
Author-email: danny@example.com
Requires-Python: >=3.11,<4.0
Classifier: License :: OSI Approved :: MIT License
Classifier: Programming Language :: Python :: 3
Classifier: Programming Language :: Python :: 3.11
Classifier: Programming Language :: Python :: 3.12
Classifier: Programming Language :: Python :: 3.13
Requires-Dist: pydantic (>=2.0.0,<3.0.0)
Project-URL: Homepage, https://github.com/Danny64Park/rcs-pydantic-automata
Project-URL: Repository, https://github.com/Danny64Park/rcs-pydantic-automata
